

{
	"name": "huceic-v2",
	"version": "1.0.0",
	"dependencies": {
		"jquery": "2.0.3",
		"backbone-amd": "1.1.0",
		"underscore-amd":	"1.5.2",
		"requirejs": "2.1.9",
		"jquery-form": "3.45.0",
		"pen": "0.0.1",
		"store": "https://github.com/marcuswestin/store.js.git",
		"jquery-placeholder":"2.0.7",
		"datetimepicker": "https://github.com/xdan/datetimepicker.git",
		"locationpicker": "https://github.com/Logicify/jquery-locationpicker-plugin.git",
		"jquery.ui": "git://github.com/jquery/jquery-ui.git", // need to run grunt build
		"owlCarousel": "https://github.com/OwlFonk/OwlCarousel.git"
	}

}